doxphinx/__init__.py
doxphinx/layout.html
doxphinx/localtoc.html
doxphinx/searchbox.html
doxphinx/theme.conf
doxphinx/ext/localtoc/__init__.py
doxphinx/ext/localtoc/localtoc.py
doxphinx/static/doxphinx.css_t
doxphinx/static/doxphinx.js_t
doxphinx-1.7.0.dist-info/COPYING
doxphinx-1.7.0.dist-info/METADATA
doxphinx-1.7.0.dist-info/WHEEL
doxphinx-1.7.0.dist-info/entry_points.txt
doxphinx-1.7.0.dist-info/top_level.txt
doxphinx-1.7.0.dist-info/RECORD
