Metadata-Version: 2.1
Name: doxphinx
Version: 1.7.0
Summary: doxphinx for Sphinx
Home-page: http://doxphinx.org/
Author: Angel Linares Zapater
Author-email: alz@phyglos.org
License: GPL version 2
Project-URL: Documentation, https://docs.phyglos.org/doxphinx/
Project-URL: Source Code, https://github.com/phyglos/doxphinx/
Keywords: doxphinx,sphinx,phyglos
Classifier: Development Status :: 5 - Production/Stable
Classifier: Framework :: Sphinx :: Extension
Classifier: Framework :: Sphinx :: Theme
Classifier: Intended Audience :: Developers
Classifier: Intended Audience :: Education
Classifier: Intended Audience :: Information Technology
Classifier: Intended Audience :: Science/Research
Classifier: Intended Audience :: System Administrators
Classifier: License :: OSI Approved :: GNU General Public License v2 (GPLv2)
Classifier: Operating System :: OS Independent
Classifier: Programming Language :: Python :: 3.7
Classifier: Topic :: Documentation
Classifier: Topic :: Software Development :: Documentation
License-File: COPYING
Requires-Dist: sphinx (>=7.0.0)
